[{"content":"本書を始める前に、まず、私に相談されたユーザーの実体験を赤で注釈しておきます。\n女性、22歳、超敏感体質 コメント1：22歳の女の子、なぜか超敏感肌？生まれたときから敏感肌だったのでしょうか？\n2）17歳からスキンケア用品を使い始め、蘭芝の角質ケアクリーム、ヒョースンギンの洗顔料、キールズのホワイトクレイ、そして何より毎日洗顔ブラシで顔を洗っていたため、こんな超敏感肌になってしまったんです。\nコメント2：敏感肌で育ったわけではないことが判明！敏感肌になる理由が判明！クレンジングブラシ、なぜクレンジングブラシで肌が敏感になるのか？\n3）16年初めに温泉でアレルギー反応を起こした。\nコメント3：肌荒れの症状が出始め、高温に耐えられなくなった。\n4）良くなってからも、肌が敏感なままだったので、コニーのバリアリペアローションとセラミドスプレーを長く使いました。\nコメント4：スキンケア製品には、傷ついたバリアーを修復する機能があるのでしょうか？ このリペア商品を使って、彼女の肌は良くなったのでしょうか？\n5）また、皮膚を厚くするために、3オプティカルという強力なパルス光を照射したこともあるそうです。 (以前、サロンでマイクロニードル、LEDライトセラピー、超音波による保湿を受けたことがあるそうです）。\nコメント5：医療行為で皮膚が厚くなることはありますか？\n(6)この正月にまた温泉に行ったが、またアレルギーが出始めた。 その後3月にまた化粧をしたのですが、以前はアレルギーもなくずっと化粧をしていたので、病院に行ってコールドスプレーとブルースキンケアを3日間してもらい、ロラタジンとグリコピロレートとパフルミンを同時に服用しました。\nコメント6：肌が不安定になり、高温やメイクが原因で肌荒れしていたそうです。 薬も使ったそうですが、治ったのでしょうか？\n(7)5月に医療美容クリニックで水分補給の注射をしたところ、肌が耐えられなかったのか、またアレルギーが出てしまい、その後また病院に行って前回と同じコールドスプレーと薬をもらいましたが、今度は今まで完治せず、背中の軽いかぶれが出ています。\nコメント7：皮膚がどんどん不安定になり、同じ薬でも効かなくなり、皮膚炎の症状が抑えられなくなりました。\n8）今はほんの少し赤くなっていて、脂漏性皮膚炎の前兆を感じています。 肌が元に戻るように、モウおじさんに助けてもらいたいです\nコメント8：自分自身を疑い始め、脂漏性皮膚炎まで考えている、どうしたら肌が修復されるのだろう？\n彼女の体験はとても感動的なものでした。 彼女は肌の調子が良かったのですが、不適切なスキンケアのせいで肌がトラブルに見舞われ、次のようなあらゆる応急処置をするようになったのです。\n補修用品の使用\n医療行為で美容院に行く\n病院の薬を使う\nしかし、数年後、かえって肌の状態が悪くなり、肌が回復することはなかった。\n● なぜ、修復剤が効かなかったのか？\nなぜ、メディカルエステは彼女の肌を修復できなかったのか？\n●なぜ、薬で不安定な皮膚を治すことができなかったのか？\n1円もかけずに彼女の肌を健康に戻せるとしたら、信じてもらえるだろうか？\n大げさではなく、あくまで肌目線で分析しているんです。 何が悪いのかがわかるから、治療もできるし、健康な状態になるまで少しずつ改善していくことができるんです。\nさて、今日は敏感肌から。\n","permalink":"https://yanwe.win/ja/post/1-geyonghudehuilianzhilu/","summary":"本書を始める前に、まず、私に相談されたユーザーの実体験を赤で注釈しておきます。 女性、22歳、超敏感体質 コメント1：22歳の女の子、なぜか超敏","title":"1.1 ユーザーの顔面破壊への道のり"},{"content":"死はしばしば不明瞭で恐ろしいものとして捉えられ、その周辺には科学的、迷信的な様々な認識が生まれている。 法医学病理学は、法医学の専門家の中で最も古く、最も重みのある分野であるが、主に死と遺体に関わるため、より神秘的な次元を与えられている。\n私が法医病理学という職業を知ったのは、映画やテレビシリーズがきっかけでした。 当時、私はまだ中学生で、毎晩夕食時にテレビで中国の犯罪捜査ドラマを放映していたのですが、「証拠を抽出して実験室で調べる」「ちゃんと科学的に分析する」など、説明のつかないシーンが多かったこと以外、正確なタイトルは今は覚えていません。 当時はまだインターネットが普及しておらず、詳しいことは分からないまま、「こんな法医学者になりたい」という野望を抱きました。 振り返れば、これは科学捜査ではない! 法医学や痕跡調査のさまざまな分野のごった煮で、ところどころ現実離れしているところもあった。\n大学受験当時、数学や物理にはほとんど興味がなかったのですが、生物と医学は好きだったので、医学部を目指そうと思っていました。 しかし、当時の私はすでに医者と患者の関係が悪く、「内向的」なところが嫌で、考えただけで疲れてしまいました。 法医学者になりたいという夢を思い出したものの、「法医学なんて、死んだ人に触るだけでしょ」と思っていました。\n大学の最初の週はどうしようもなかった、高等数学と物理は100回くらい死んでもおかしくない。 私は「鑑識の夢」を思い出した。 先生や先輩とのコミュニケーション、面接、専門科目の傍聴などを通じて、「法医学を学ばなければならない」と確信しました。 幸い、この学校には専攻を移すという方針があり、私は無事に法医学教室に移ることができました。\n法医学に長年携わっていると、「どうしてそんな職業を選んだのですか」と、ためらいや戸惑いをもって質問されることが多く、この職業についてわからないことがたくさんあることに気づかされます。 科学捜査への思いから、より多くの人に本当の科学捜査を知ってもらい、非科学的で間違った認識を解き明かし、この不思議な職業をもっとリアルに紹介したいと思い、インターネットで科学捜査の普及に努めました。 そして、当時の私のように夢を持ちながら、それを理解する術を持たない子供たちに、少しでも痕跡を残し、ささやかな手助けをすることです。\n仕事柄、文章では事件に触れないようにし、専門的な内容もシンプルでわかりやすい生活用語で説明することを心がけてきました。 この手の文章は飽きやすく、かわいくて面白い文体でも、たまの気分転換にしかならず、かといって読み過ぎると飽きてしまうのが正直なところです。\nそこで今回、熟慮の末、法医学に関する電子書籍を執筆することになったのですが、具体的な事例を通じて、法医学の知識の実用性を示すつもりでいます。 芸術は生活から生まれ、生活より高い」という言葉があるように、私の拙い文章は芸術というほどのものではありませんが、理屈は同じ、すなわち「芸術」です。\nこの記事に関わるストーリーは、時間、人名、地名、細部などすべてが架空のものであり、人工的な加工とフィクションによって表現されています。 世の中は驚きに満ちていて、偶然が起こるのは当たり前ですから、現実と一緒にしないでください。\n","permalink":"https://yanwe.win/ja/post/1.xiezaiqianmian/","summary":"死はしばしば不明瞭で恐ろしいものとして捉えられ、その周辺には科学的、迷信的な様々な認識が生まれている。 法医学病理学は、法医学の専門家の中で最","title":"1.前面に書き込む"},{"content":"この世のすべての物事には、初めてというものがある。 緊張する初体験もあれば、驚きと喜びの初体験もあり、圧倒的に悲しい初体験もある。 私の場合、フォレンジックワークとの出会いは、上記のすべてとはちょっと違いました。\n私が初めてフォレンジックワークに触れたのは、大学1年生の夏でした。 インターンシップを割り当ててくれる公安局の鑑識課長に先輩を通じて連絡し、まずは鑑識の仕事を体験できる部隊を手配してもらうようにお願いしました。 それで、公安局に行って、鑑識の研修生として働き始めたんです。\n初日に院長から「法医病理学」を投げられ、「まだ大学1年で、こういう専門的なことを学ぶのは早いから自分で読みなさい」と言われ、実はほとんど理解できないまま読んでいたのですが、「法医病理学」を読んでみて、「なるほど」と思いました。 夜は、見習いという貴重な機会を逃すまいと、その日の当番の先輩に「何かあったら呼んでくれ」と頼んで、アパートに泊まることにしたのです。 しかし、数日続けて、何か気になることがあり、眠れないという感覚は耐え難いものでした。\nある日、ついに人生初のライブが実現したのですが、興奮のあまり、まさか初ライブがかなりヘビーなものになるとは思ってもいませんでした。\nその日の朝5時過ぎ、ぐっすり眠っていたら、枕元で突然携帯電話が鳴った。 ベッドから飛び起きて電話を取ると、その日の当番の監督からで、下に集合してくれ、現場があるとのことだった。\nすぐに起き上がり、服を着て、エレベーターを待つのが遅かったので、階段で急いで1階に降りた。 しかし、コオロギの鳴く階下で一人、数分待っていると、ディレクターが二人であくびをしながら出てくるのが見えました。 私の前向きな姿勢にとても感謝していると同時に、「若い人はエネルギーがある」「もう古い」・・・と、それぞれ入社当時の情熱を思い出していました。\n現場は、農村部から都市部にかけての道路の歩道上にある商店の前だった。 現場に着くと、周りには野次馬がたくさんいて、先に到着した交番の警察がすでに非常線を張り、野次馬を退散させようとしていたが、無駄だった。\n\u0026ldquo;トランクから調査箱を出してきて\u0026rdquo; チーフに言われ、車から降りて事情を聞いた。\n鑑識調査」と印刷された大きな箱を取り出し、交番の列を折り曲げて中に入った。 周りの多くの野次馬の視線と手にしたケースを感じ、脚光を浴びることができたのです\n現場に近づくと、まず赤い傘が立てかけてあり、その傘の下には掛け布団があり、その下に人がいるのが見えました。 故人の娘と名乗る中年女性は泣きながら言った。「朝\u0026hellip;\u0026hellip;起きたばかり\u0026hellip;\u0026hellip;日に\u0026hellip;\u0026hellip;下の方で音がして\u0026hellip;\u0026hellip;」。 \u0026hellip;階下の誰かが「人が死んだ」と叫んでいたので、窓から身を乗り出して見てみると\u0026hellip;\u0026hellip;母の服を着た人が地面に倒れていた\u0026hellip;\u0026hellip;降りると、それは母だった\u0026hellip;\u0026hellip;\u0026hellip;。 \u0026hellip;\u0026hellip;お母さん\u0026hellip;\u0026hellip;なんで飛び降り自殺したの！！！！\u0026quot;\n現場調査の同僚が現場修正のために写真を撮っている間に調査ボックスを開け、手袋を取り出して監督に一組渡し、自分も一組はめてみた。 写真撮影が終わると、監督が歩み寄ってきて、毛糸の帽子を持ち上げてくれた。\n\u0026ldquo;これは脳の組織だ\u0026rdquo; 監督は遺体の横にしゃがみ込みながら、「後で覚悟しておけよ」と言った。\n監督が傘を動かそうとすると、故人の娘さんが駆け寄ってきて、「死んだ人が太陽に顔を見せてはいけない！」と制止されました。 どんな迷信だ」と心の中でつぶやいた。 と同時に監督を見た。\n監督は立ち上がり、故人の娘さんに「お気持ちはわかりますが、今はお母さんの死因を調べるために状況を確認しなければなりません、もし誰かがお母さんを殺したとしたらどうしますか？ 監督は何度も言い返したが、故人の娘さんは「亡くなった人は太陽に顔を見せてはいけない！」と繰り返すばかりだった。\nコミュニケーションがうまくいっていないと見た監督は、警察を呼んで故人の娘さんを脇に呼んで状況を記録し、私に向かって「傘を持って覆い、毛布を少し持ち上げて、まず私が状況を確認する」と言ったのです。 私はしゃがみこみ、片手で傘を持ち、もう片方の手で掛け布団の角を床から浮かせました。\n掛け布団の下には、血に染まった歪んだ顔があり、よく見ると血の中には白い脳組織が混じっていた。 院長は死体の頭を触って小声で言った。「見てください、この頭は変形しています、まだ多くの骨折があるのが感じられます、左側の頭皮の大きな部分はこんなに大きく裂けています・・・・・・」彼は指で突っ込みながら言った。 \u0026ldquo;えーと\u0026hellip;\u0026hellip;頭蓋骨の奥の方で、ここから脳組織が出てるんです。\u0026rdquo; その後、監督は肋骨や手足を診ていきましたが、故人の右肘は監督の手の下で変な形に捻られており、確かに骨折しているように見えました。 院長は診察を終えると掛け布団をかけ直し、傘を元の位置に戻すように私に言い、私と故人の娘に「上を見てこよう」と声をかけ、建物の奥にあるアパートの扉に向かって歩いていきました。\n4階に着くと、そこに小さなドアがあったので、上がってみると、空き地の向こう側にカラフルな鉄板でできた仮設のキュービックと、洗濯物が数枚干してある屋上がありました。 故人の娘さんがやってきて、「あそこの部屋には母が住んでいました」と指さす。 トレース調査の同僚が写真を撮ったり、床をチェックしたりしているのが見えたので、私も行って見てみたのですが、部屋は少し物が多いものの、きちんと整理されており、目立った不具合はありませんでした。\n\u0026ldquo;写真を撮りに来てください\u0026rdquo; 監督の声がして振り返ると、屋上の壁際にあるベンチがひっくり返ったところに行き、監督が体の半分を突き出して下を向いて、「誰か撮りに来てください」と呼びかけていました。 また、外を見てみると、下の死人と全く逆の位置であったが、他に特に異常は見られなかった。 もう少し突き出そうとしたところで、ディレクターが手を伸ばして止めてくれた。\n\u0026ldquo;こすらない \u0026ldquo;に注意! 見てください、これ！」。 監督が指差した先には、ちょうど私が擦れたフェンスがあった。\n\u0026ldquo;これは\u0026hellip;\u0026hellip;足跡か？\u0026rdquo; 監督の手を追ってフェンスに向かうと、かすかに目立たない跡があり、観察する角度を変えると、前足の裏の模様のようなものを発見した。\n\u0026ldquo;足跡 \u0026ldquo;なんです。 さあ、あなたの考えを聞かせてください。\u0026rdquo; ディレクターは私の顔を見て言った。\n被害者はここから飛び降りたのだろう！」と思いました。\n監督は「まあ、それはほんの一部ですが」と頷いた。 でも、気づかなかったディテールがあるはず\u0026hellip;もう一度、外の軒先にあるものを見てみてください。\n改めて外を見ると、屋上の外には釉薬瓦でできた小さな庇が10センチほど出ているだけで、庇の上には小さな埃がこすり落とされ、その下のきれいな瓦が見えているのである。\n\u0026ldquo;男が飛び降りたのなら、なぜ軒先の埃はこすり落とされたと思う？\u0026rdquo;\n私の困惑した顔を見て、監督は「初めてのことだからわからなくて当然だ」と続けました。 故人はかなり高齢の女性で、先ほど診察したところ、体の筋肉の萎縮がひどく、生前は長い間寝たきりで、体もかなり弱っているはずであった。 このフェンスを登るのも大変なのに、どうして「ジャンプ」する力があるのだろう。 塀をよじ登り、軒先に頭から滑り落ちたのだろう。\n\u0026ldquo;署長、彼女が頭から滑り落ちて、抱き上げられて投げ落とされたのではないと、どうして確信できるのですか？\u0026rdquo; と質問した。\n監督は「とても良い！」と褒めてくれました。 よく考えていらっしゃいますね。 周囲の地面は非常に粗いコンクリートで、目に見える足跡は残りにくいし、洗濯物を干していた場所の隣なので、故人以外の足跡があってもおかしくはないのだそうです。 しかし、ベンチと台の両方の端に1つだけ足跡があり、模様も似ていたので、故人はひっくり返ったベンチを踏み、自分で柵をよじ登ったと推定されます。 なぜ頭が下がっていたのかは、あなたが教えてください」。\n\u0026ldquo;まあ！ 昨日いただいた本に、『着地した部位と受けた傷には密接な関係がある』と書いてあったばかりです。 監督の顔を見ながら慎重に言ったところ、ゆっくりうなずいてくれたので、少し自信がつきました。 私は続けて、\u0026ldquo;先ほど、被害者の頭部と手足の傷は明らかだったので、頭から落ちたのだろうと推測されました。\u0026ldquo;と述べました。\n\u0026ldquo;とても良い! 法医学者としてあらゆる現象や細かい情報を組み合わせる必要がありますが、これには経験を積むための練習が必要で、このような思考を自分の頭で頻繁に行う必要があるのです。\u0026rdquo; 監督は少し笑って、「さあ、ここは特に異常は見られないから、自殺したのはおばあさんだろう。 もう一度、家族に聞いて見よう』。\n再び故人の娘さんを見つけ、私たちが考えていることを説明すると、娘さんは疑惑の声を上げてくれた。 半年以上前に癌を宣告され、家を売りに出しても効果がなく、貯金を使い果たし、住むところもなく、仕方なく親戚の家に行ったが、住むことができず、屋上に仮設住宅を建てたそうです。 この後、お婆さんの体調は日に日に悪くなっていった。\n故人の娘さんは、母が住んでいた場所を見て、最後に「母はこれ以上、私たちの足を引っ張らないようにと思ったんでしょうね」と言った。\n初めて現場に出て、初めて本当の死を目の当たりにした。\n入学して1年目で解剖学を終えたばかりの私ですが、すでに死体を見たり、自分で解剖をしたこともありましたが、やはりホルマリン処理された死体で、初めて見たときはまだショックでしたが、学期が進むにつれ慣れてきて、まるで毎日先生を見ているような感じになってきました。 しかし、今回は実際に自分の周りで死を目の当たりにし、家族の悲しみを肌で感じることができました。\n帰り道、車の中で少しボーっとしている私を見て、チーフが「こんな光景は初めてだろう？ 警察の仕事は地に足の着いた仕事で、社会の暗部をたくさん見ることができます。 人が死ぬと、人間の気持ちや温かさがたくさん出てきます。 将来、法医学者になれば、暗いことやネガティブなことに遭遇することが多くなるので、心を平静に保つことを学ばなければなりません。\n今は、警察官ではなく、法医学者としても働いています。 当時、監督がおっしゃったことをいつも心に刻み、実践してきました。\n","permalink":"https://yanwe.win/ja/post/2.fayishengyadediyicixianchang/","summary":"この世のすべての物事には、初めてというものがある。 緊張する初体験もあれば、驚きと喜びの初体験もあり、圧倒的に悲しい初体験もある。 私の場合、フ","title":"2.フォレンジックキャリアの「最初の」現場"}]